wad/__init__.py
wad/__version__.py
wad/core.py
what_a_dict-0.1.1.dist-info/LICENSE
what_a_dict-0.1.1.dist-info/METADATA
what_a_dict-0.1.1.dist-info/WHEEL
what_a_dict-0.1.1.dist-info/top_level.txt
what_a_dict-0.1.1.dist-info/RECORD
