Metadata-Version: 2.1
Name: what-a-dict
Version: 0.1.1
Summary: Dictionary class with advanced functionality
Home-page: https://github.com/ShuYuHuang/what-a-dict
Author: ShuYuHuang
Author-email: b123767195@gmail.com
License: MIT
Platform: UNKNOWN
Classifier: License :: OSI Approved :: MIT License
Classifier: Programming Language :: Python
Classifier: Programming Language :: Python :: 3
Classifier: Programming Language :: Python :: 3.6
Classifier: Programming Language :: Python :: Implementation :: CPython
Classifier: Programming Language :: Python :: Implementation :: PyPy
Requires-Python: >=3.6.0
License-File: LICENSE
